zorglangue_traductor/__init__.py
zorglangue_traductor/main.py
zorglangue_traductor/utils/__init__.py
zorglangue_traductor/utils/lower_upper.py
zorglangue_traductor/utils/shift.py
zorglangue_traductor-2.0.0.dist-info/METADATA
zorglangue_traductor-2.0.0.dist-info/WHEEL
zorglangue_traductor-2.0.0.dist-info/licenses/LICENSE
zorglangue_traductor-2.0.0.dist-info/RECORD
