Metadata-Version: 2.1
Name: zorglangue_traductor
Version: 2.0.0
Summary: A Python module that allows you to traduce the fake language Zorglangue from the Spirou comic strips. Works from a Latin language (originally French) to Zorglangue and vice versa. Eviv Bulgroz !
Project-URL: Homepage, https://github.com/raphaeldenni/zorglangue-traductor
Project-URL: Bug Tracker, https://github.com/raphaeldenni/zorglangue-traductor/issues
Author: Raphaël Denni
License: MIT License
License-File: LICENSE
Classifier: License :: OSI Approved :: MIT License
Classifier: Operating System :: Microsoft :: Windows
Classifier: Programming Language :: Python :: 3
Requires-Python: >=3.0
